maildesk/__init__.py
maildesk/client.py
maildesk-0.1.1.dist-info/LICENSE
maildesk-0.1.1.dist-info/METADATA
maildesk-0.1.1.dist-info/WHEEL
maildesk-0.1.1.dist-info/top_level.txt
maildesk-0.1.1.dist-info/RECORD
