Metadata-Version: 2.1
Name: maildesk
Version: 0.1.1
Summary: email python library
Home-page: https://github.com/khezen/maildesk
Author: Guillaume Simonneau
Author-email: simonneaug@gmail.com
License: UNKNOWN
Platform: UNKNOWN
Classifier: Programming Language :: Python :: 3
Classifier: License :: OSI Approved :: MIT License
Classifier: Operating System :: OS Independent
Requires-Python: >=2.7
